[
    { "op": "add", "path": "/allowedVariants/-", "value": "looseores-cerussite-limestone-free", "file": "game:blocktypes/stone/looseores.json" },
	{ "op": "add", "path": "/allowedVariants/-", "value": "looseores-cerussite-aragonite-free", "file": "game:blocktypes/stone/looseores.json" },
	{ "op": "add", "path": "/allowedVariants/-", "value": "looseores-cerussite-calcite-free", "file": "game:blocktypes/stone/looseores.json" },
	{ "op": "add", "path": "/allowedVariants/-", "value": "looseores-cerussite-dolomite-free", "file": "game:blocktypes/stone/looseores.json" },
	{ "op": "add", "path": "/allowedVariants/-", "value": "looseores-cerussite-chalk-free", "file": "game:blocktypes/stone/looseores.json" },
	{ "op": "add", "path": "/allowedVariants/-", "value": "looseores-cerussite-bauxite-free", "file": "game:blocktypes/stone/looseores.json" },
	{ "op": "add", "path": "/allowedVariants/-", "value": "looseores-cerussite-claystone-free", "file": "game:blocktypes/stone/looseores.json" },
	{ "op": "add", "path": "/allowedVariants/-", "value": "looseores-cerussite-sandstone-free", "file": "game:blocktypes/stone/looseores.json" },

	{ "op": "add", "path": "/allowedVariants/-", "value": "ore-poor-cerussite-limestone", "file": "game:itemtypes/resource/ore-graded.json" },
	{ "op": "add", "path": "/allowedVariants/-", "value": "ore-medium-cerussite-limestone", "file": "game:itemtypes/resource/ore-graded.json" },
	{ "op": "add", "path": "/allowedVariants/-", "value": "ore-rich-cerussite-limestone", "file": "game:itemtypes/resource/ore-graded.json" },
	{ "op": "add", "path": "/allowedVariants/-", "value": "ore-bountiful-cerussite-limestone", "file": "game:itemtypes/resource/ore-graded.json" },
	{ "op": "add", "path": "/allowedVariants/-", "value": "ore-poor-cerussite-aragonite", "file": "game:itemtypes/resource/ore-graded.json" },
	{ "op": "add", "path": "/allowedVariants/-", "value": "ore-medium-cerussite-aragonite", "file": "game:itemtypes/resource/ore-graded.json" },
	{ "op": "add", "path": "/allowedVariants/-", "value": "ore-rich-cerussite-aragonite", "file": "game:itemtypes/resource/ore-graded.json" },
	{ "op": "add", "path": "/allowedVariants/-", "value": "ore-bountiful-cerussite-aragonite", "file": "game:itemtypes/resource/ore-graded.json" },
	{ "op": "add", "path": "/allowedVariants/-", "value": "ore-poor-cerussite-calcite", "file": "game:itemtypes/resource/ore-graded.json" },
	{ "op": "add", "path": "/allowedVariants/-", "value": "ore-medium-cerussite-calcite", "file": "game:itemtypes/resource/ore-graded.json" },
	{ "op": "add", "path": "/allowedVariants/-", "value": "ore-rich-cerussite-calcite", "file": "game:itemtypes/resource/ore-graded.json" },
	{ "op": "add", "path": "/allowedVariants/-", "value": "ore-bountiful-cerussite-calcite", "file": "game:itemtypes/resource/ore-graded.json" },
	{ "op": "add", "path": "/allowedVariants/-", "value": "ore-poor-cerussite-dolomite", "file": "game:itemtypes/resource/ore-graded.json" },
	{ "op": "add", "path": "/allowedVariants/-", "value": "ore-medium-cerussite-dolomite", "file": "game:itemtypes/resource/ore-graded.json" },
	{ "op": "add", "path": "/allowedVariants/-", "value": "ore-rich-cerussite-dolomite", "file": "game:itemtypes/resource/ore-graded.json" },
	{ "op": "add", "path": "/allowedVariants/-", "value": "ore-bountiful-cerussite-dolomite", "file": "game:itemtypes/resource/ore-graded.json" },
	{ "op": "add", "path": "/allowedVariants/-", "value": "ore-poor-cerussite-chalk", "file": "game:itemtypes/resource/ore-graded.json" },
	{ "op": "add", "path": "/allowedVariants/-", "value": "ore-medium-cerussite-chalk", "file": "game:itemtypes/resource/ore-graded.json" },
	{ "op": "add", "path": "/allowedVariants/-", "value": "ore-rich-cerussite-chalk", "file": "game:itemtypes/resource/ore-graded.json" },
	{ "op": "add", "path": "/allowedVariants/-", "value": "ore-poor-cerussite-bauxite", "file": "game:itemtypes/resource/ore-graded.json" },
	{ "op": "add", "path": "/allowedVariants/-", "value": "ore-medium-cerussite-bauxite", "file": "game:itemtypes/resource/ore-graded.json" },
	{ "op": "add", "path": "/allowedVariants/-", "value": "ore-rich-cerussite-bauxite", "file": "game:itemtypes/resource/ore-graded.json" },
	{ "op": "add", "path": "/allowedVariants/-", "value": "ore-poor-cerussite-claystone", "file": "game:itemtypes/resource/ore-graded.json" },
	{ "op": "add", "path": "/allowedVariants/-", "value": "ore-medium-cerussite-claystone", "file": "game:itemtypes/resource/ore-graded.json" },
	{ "op": "add", "path": "/allowedVariants/-", "value": "ore-rich-cerussite-claystone", "file": "game:itemtypes/resource/ore-graded.json" },
	{ "op": "add", "path": "/allowedVariants/-", "value": "ore-poor-cerussite-sandstone", "file": "game:itemtypes/resource/ore-graded.json" },
	{ "op": "add", "path": "/allowedVariants/-", "value": "ore-medium-cerussite-sandstone", "file": "game:itemtypes/resource/ore-graded.json" },
	{ "op": "add", "path": "/allowedVariants/-", "value": "ore-rich-cerussite-sandstone", "file": "game:itemtypes/resource/ore-graded.json" },

	{ "op": "add", "path": "/allowedVariants/-", "value": "crystalizedore-poor-cerussite-limestone", "file": "game:itemtypes/resource/crystalizedore-graded.json" },
	{ "op": "add", "path": "/allowedVariants/-", "value": "crystalizedore-medium-cerussite-limestone", "file": "game:itemtypes/resource/crystalizedore-graded.json" },
	{ "op": "add", "path": "/allowedVariants/-", "value": "crystalizedore-rich-cerussite-limestone", "file": "game:itemtypes/resource/crystalizedore-graded.json" },
	{ "op": "add", "path": "/allowedVariants/-", "value": "crystalizedore-bountiful-cerussite-limestone", "file": "game:itemtypes/resource/crystalizedore-graded.json" },
	{ "op": "add", "path": "/allowedVariants/-", "value": "crystalizedore-poor-cerussite-aragonite", "file": "game:itemtypes/resource/crystalizedore-graded.json" },
	{ "op": "add", "path": "/allowedVariants/-", "value": "crystalizedore-medium-cerussite-aragonite", "file": "game:itemtypes/resource/crystalizedore-graded.json" },
	{ "op": "add", "path": "/allowedVariants/-", "value": "crystalizedore-rich-cerussite-aragonite", "file": "game:itemtypes/resource/crystalizedore-graded.json" },
	{ "op": "add", "path": "/allowedVariants/-", "value": "crystalizedore-bountiful-cerussite-aragonite", "file": "game:itemtypes/resource/crystalizedore-graded.json" },
	{ "op": "add", "path": "/allowedVariants/-", "value": "crystalizedore-poor-cerussite-calcite", "file": "game:itemtypes/resource/crystalizedore-graded.json" },
	{ "op": "add", "path": "/allowedVariants/-", "value": "crystalizedore-medium-cerussite-calcite", "file": "game:itemtypes/resource/crystalizedore-graded.json" },
	{ "op": "add", "path": "/allowedVariants/-", "value": "crystalizedore-rich-cerussite-calcite", "file": "game:itemtypes/resource/crystalizedore-graded.json" },
	{ "op": "add", "path": "/allowedVariants/-", "value": "crystalizedore-bountiful-cerussite-calcite", "file": "game:itemtypes/resource/crystalizedore-graded.json" },
	{ "op": "add", "path": "/allowedVariants/-", "value": "crystalizedore-poor-cerussite-dolomite", "file": "game:itemtypes/resource/crystalizedore-graded.json" },
	{ "op": "add", "path": "/allowedVariants/-", "value": "crystalizedore-medium-cerussite-dolomite", "file": "game:itemtypes/resource/crystalizedore-graded.json" },
	{ "op": "add", "path": "/allowedVariants/-", "value": "crystalizedore-rich-cerussite-dolomite", "file": "game:itemtypes/resource/crystalizedore-graded.json" },
	{ "op": "add", "path": "/allowedVariants/-", "value": "crystalizedore-bountiful-cerussite-dolomite", "file": "game:itemtypes/resource/crystalizedore-graded.json" },
	{ "op": "add", "path": "/allowedVariants/-", "value": "crystalizedore-poor-cerussite-chalk", "file": "game:itemtypes/resource/crystalizedore-graded.json" },
	{ "op": "add", "path": "/allowedVariants/-", "value": "crystalizedore-medium-cerussite-chalk", "file": "game:itemtypes/resource/crystalizedore-graded.json" },
	{ "op": "add", "path": "/allowedVariants/-", "value": "crystalizedore-rich-cerussite-chalk", "file": "game:itemtypes/resource/crystalizedore-graded.json" },
	{ "op": "add", "path": "/allowedVariants/-", "value": "crystalizedore-poor-cerussite-bauxite", "file": "game:itemtypes/resource/crystalizedore-graded.json" },
	{ "op": "add", "path": "/allowedVariants/-", "value": "crystalizedore-medium-cerussite-bauxite", "file": "game:itemtypes/resource/crystalizedore-graded.json" },
	{ "op": "add", "path": "/allowedVariants/-", "value": "crystalizedore-rich-cerussite-bauxite", "file": "game:itemtypes/resource/crystalizedore-graded.json" },
	{ "op": "add", "path": "/allowedVariants/-", "value": "crystalizedore-poor-cerussite-claystone", "file": "game:itemtypes/resource/crystalizedore-graded.json" },
	{ "op": "add", "path": "/allowedVariants/-", "value": "crystalizedore-medium-cerussite-claystone", "file": "game:itemtypes/resource/crystalizedore-graded.json" },
	{ "op": "add", "path": "/allowedVariants/-", "value": "crystalizedore-rich-cerussite-claystone", "file": "game:itemtypes/resource/crystalizedore-graded.json" },
	{ "op": "add", "path": "/allowedVariants/-", "value": "crystalizedore-poor-cerussite-sandstone", "file": "game:itemtypes/resource/crystalizedore-graded.json" },
	{ "op": "add", "path": "/allowedVariants/-", "value": "crystalizedore-medium-cerussite-sandstone", "file": "game:itemtypes/resource/crystalizedore-graded.json" },
	{ "op": "add", "path": "/allowedVariants/-", "value": "crystalizedore-rich-cerussite-sandstone", "file": "game:itemtypes/resource/crystalizedore-graded.json" },

	{ "op": "add", "path": "/allowedVariants/-", "value": "ore-poor-cerussite-limestone", "file": "game:blocktypes/stone/ore-graded.json" },
	{ "op": "add", "path": "/allowedVariants/-", "value": "ore-medium-cerussite-limestone", "file": "game:blocktypes/stone/ore-graded.json" },
	{ "op": "add", "path": "/allowedVariants/-", "value": "ore-rich-cerussite-limestone", "file": "game:blocktypes/stone/ore-graded.json" },
	{ "op": "add", "path": "/allowedVariants/-", "value": "ore-bountiful-cerussite-limestone", "file": "game:blocktypes/stone/ore-graded.json" },
	{ "op": "add", "path": "/allowedVariants/-", "value": "ore-poor-cerussite-aragonite", "file": "game:blocktypes/stone/ore-graded.json" },
	{ "op": "add", "path": "/allowedVariants/-", "value": "ore-medium-cerussite-aragonite", "file": "game:blocktypes/stone/ore-graded.json" },
	{ "op": "add", "path": "/allowedVariants/-", "value": "ore-rich-cerussite-aragonite", "file": "game:blocktypes/stone/ore-graded.json" },
	{ "op": "add", "path": "/allowedVariants/-", "value": "ore-bountiful-cerussite-aragonite", "file": "game:blocktypes/stone/ore-graded.json" },
	{ "op": "add", "path": "/allowedVariants/-", "value": "ore-poor-cerussite-calcite", "file": "game:blocktypes/stone/ore-graded.json" },
	{ "op": "add", "path": "/allowedVariants/-", "value": "ore-medium-cerussite-calcite", "file": "game:blocktypes/stone/ore-graded.json" },
	{ "op": "add", "path": "/allowedVariants/-", "value": "ore-rich-cerussite-calcite", "file": "game:blocktypes/stone/ore-graded.json" },
	{ "op": "add", "path": "/allowedVariants/-", "value": "ore-bountiful-cerussite-calcite", "file": "game:blocktypes/stone/ore-graded.json" },
	{ "op": "add", "path": "/allowedVariants/-", "value": "ore-poor-cerussite-dolomite", "file": "game:blocktypes/stone/ore-graded.json" },
	{ "op": "add", "path": "/allowedVariants/-", "value": "ore-medium-cerussite-dolomite", "file": "game:blocktypes/stone/ore-graded.json" },
	{ "op": "add", "path": "/allowedVariants/-", "value": "ore-rich-cerussite-dolomite", "file": "game:blocktypes/stone/ore-graded.json" },
	{ "op": "add", "path": "/allowedVariants/-", "value": "ore-bountiful-cerussite-dolomite", "file": "game:blocktypes/stone/ore-graded.json" },
	{ "op": "add", "path": "/allowedVariants/-", "value": "ore-poor-cerussite-chalk", "file": "game:blocktypes/stone/ore-graded.json" },
	{ "op": "add", "path": "/allowedVariants/-", "value": "ore-medium-cerussite-chalk", "file": "game:blocktypes/stone/ore-graded.json" },
	{ "op": "add", "path": "/allowedVariants/-", "value": "ore-rich-cerussite-chalk", "file": "game:blocktypes/stone/ore-graded.json" },
	{ "op": "add", "path": "/allowedVariants/-", "value": "ore-poor-cerussite-bauxite", "file": "game:blocktypes/stone/ore-graded.json" },
	{ "op": "add", "path": "/allowedVariants/-", "value": "ore-medium-cerussite-bauxite", "file": "game:blocktypes/stone/ore-graded.json" },
	{ "op": "add", "path": "/allowedVariants/-", "value": "ore-rich-cerussite-bauxite", "file": "game:blocktypes/stone/ore-graded.json" },
	{ "op": "add", "path": "/allowedVariants/-", "value": "ore-poor-cerussite-claystone", "file": "game:blocktypes/stone/ore-graded.json" },
	{ "op": "add", "path": "/allowedVariants/-", "value": "ore-medium-cerussite-claystone", "file": "game:blocktypes/stone/ore-graded.json" },
	{ "op": "add", "path": "/allowedVariants/-", "value": "ore-rich-cerussite-claystone", "file": "game:blocktypes/stone/ore-graded.json" },
	{ "op": "add", "path": "/allowedVariants/-", "value": "ore-poor-cerussite-sandstone", "file": "game:blocktypes/stone/ore-graded.json" },
	{ "op": "add", "path": "/allowedVariants/-", "value": "ore-medium-cerussite-sandstone", "file": "game:blocktypes/stone/ore-graded.json" },
	{ "op": "add", "path": "/allowedVariants/-", "value": "ore-rich-cerussite-sandstone", "file": "game:blocktypes/stone/ore-graded.json" },

    { "op": "add", "path": "/requiredMiningTierByType/ore-*-cerussite-*", "value": 2, "file": "game:blocktypes/stone/ore-graded.json" },
    { "op": "add", "path": "/variants/-", "value": { "Code": "cerussite" }, "file": "game:worldproperties/block/ore-graded.json" },
	{ "op": "add", "path": "/variants/-", "value": { "Code": "cerussite" }, "file": "game:worldproperties/block/ore-nugget.json" },
    {
        "op": "add", "path": "/combustiblePropsByType/*-cerussite", 
        "value": { 
            "meltingPoint": 315, "meltingDuration": 30, "smeltedRatio": 20, 
            "smeltedStack": { "type": "item", "code": "ingot-lead" } 
        }, 
        "file": "game:itemtypes/resource/nugget.json" 
    }
]